[
    {
        "startTime":"09:00 AM",
        "topic":"Registration",
        "tag":"",
        "des":"Register yourself and confirm your participation on the Help-desks."
    },
    {
        "startTime":"09:30 AM",
        "topic":"Welcome Keynote",
        "tag":"",
        "des":"Brief intro about the organization, event, agenda, etc."
    },
    {
        "startTime":"09:45 AM",
        "topic":"Information Architecture and it's impact on UX Design",
        "tag":"Design",
        "des":"User Experience of any tech product depends on how well we humanise the language."
    },
    {
        "startTime":"10:25 AM",
        "topic":"Product showcase - ParkiN",
        "tag":"Product Demo",
        "des":""
    },
    {
        "startTime":"10:35 AM",
        "topic":"#IamRemarkable Workshop",
        "tag":"Workshop",
        "des":"#IamRemarkable is a Google initiative empowering women and underrepresented groups to celebrate their achievements in the workplace and beyond."
    },
    {
        "startTime":"11:45 AM",
        "topic":"Product showcase - Firecamp",
        "tag":"Product Demo",
        "des":""
    },
    {
        "startTime":"11:55 AM",
        "topic":"Minimalism - The pursuit of less",
        "tag":"Personal Branding",
        "des":"The quintessential skill in the rapidly expanding world of today - how you package yourself, communicate your unique skills and the value you bring to an organisation."
    },
    {
        "startTime":"12:35 AM",
        "topic":"Surprise session",
        "tag":"",
        "des":""
    },
    {
        "startTime":"12:50 AM",
        "topic":"Women-O-Sphere Activitty",
        "tag":"Fun",
        "des":"Let's enjoy a bit before taking delicious lunch."
    },
    {
        "startTime":"01:00 AM",
        "topic":"Lunch",
        "tag":"",
        "des":"Increase the energy level again to enjoy the upcoming awesome workshops."
    },
    {
        "startTime":"01:45 AM",
        "topic":"Product showcase - S.E.T.U",
        "tag":"Product Demo",
        "des":""
    },
    {
        "startTime":"02:00 AM",
        "topic":"Flutter Codelab / Networking",
        "tag":"Flutter",
        "des":"This codelab provides a deeper dive into Flutter."
    },
    {
        "startTime":"04:00 AM",
        "topic":"Thanks note and Good bye!",
        "tag":"",
        "des":""
    }
]